nonebot_plugin_wakeup_timetable/__init__.py
nonebot_plugin_wakeup_timetable/config.py
nonebot_plugin_wakeup_timetable/get.py
nonebot_plugin_wakeup_timetable/migrations/2bb8e94da48e_init.py
nonebot_plugin_wakeup_timetable/models.py
nonebot_plugin_wakeup_timetable/render.py
nonebot_plugin_wakeup_timetable/utils.py
nonebot_plugin_wakeup_timetable-0.1.0.dist-info/LICENSE
nonebot_plugin_wakeup_timetable-0.1.0.dist-info/METADATA
nonebot_plugin_wakeup_timetable-0.1.0.dist-info/WHEEL
nonebot_plugin_wakeup_timetable-0.1.0.dist-info/RECORD
